homeconnect/__init__.py
homeconnect/api.py
homeconnect/sseclient.py
tests/__init__.py
tests/homeconnect/__init__.py
tests/homeconnect/test_api.py
homeconnect-0.8.0.dist-info/LICENSE
homeconnect-0.8.0.dist-info/METADATA
homeconnect-0.8.0.dist-info/WHEEL
homeconnect-0.8.0.dist-info/top_level.txt
homeconnect-0.8.0.dist-info/RECORD
