Metadata-Version: 2.1
Name: homeconnect
Version: 0.8.0
Summary: Python client for the BSH Home Connect REST API
Home-page: https://github.com/DavidMStraub/homeconnect
Author: David M. Straub
Author-email: straub@protonmail.com
License: MIT
License-File: LICENSE
Requires-Dist: requests
Requires-Dist: requests-oauthlib
Provides-Extra: testing
Requires-Dist: nose ; extra == 'testing'
